libfilter/__init__.py
libfilter/afte_encoder.py
libfilter/audio_filters.py
libfilter/base_classes.py
libfilter/data_encoders.py
libfilter/decoders.py
libfilter/encoders.py
libfilter/modulators.py
libfilter/oscillators.py
libfilter/other.py
libfilter/samplers.py
libfilter/transformers.py
libfilter-1.37.dist-info/LICENCE
libfilter-1.37.dist-info/METADATA
libfilter-1.37.dist-info/WHEEL
libfilter-1.37.dist-info/top_level.txt
libfilter-1.37.dist-info/RECORD
