Metadata-Version: 2.1
Name: libfilter
Version: 1.37
Summary: Signal/Audio Processing framework made with pure python
Home-page: https://github.com/KubaPro010/libfilter
Author: kuba201
Project-URL: Source, https://github.com/KubaPro010/libfilter
Keywords: fm,processor,pcm,signal
Classifier: Intended Audience :: Education
Classifier: Intended Audience :: Telecommunications Industry
Classifier: Programming Language :: Python :: 3 :: Only
Classifier: Programming Language :: Python :: 3.10
Classifier: Development Status :: 5 - Production/Stable
Classifier: License :: OSI Approved :: GNU General Public License (GPL)
License-File: LICENCE
